{
    "recipes": [
        {
            "id": "heartinduction",
            "label": "心之行程",
            "actionId": "heartinduction",
            "effects": {
                "previtality": 1
            },
            "startdescription": "每當心之準則浮現時，我便可以獲得<b>活力</b>。",
            "description": "今天，我自己的心臟搏動地更有力了。",
            "warmup": 30,
            "craftable": false
        },
        {
            "id": "lanterninduction",
            "label": "顱內之光",
            "actionId": "lanterninduction",
            "effects": {
                "preerudition": 1
            },
            "startdescription": "每當燈之準則放光時，我便可以多記起一些殘篇知識。",
            "description": "腦海中的灰塵一掃而空，至少暫時如此。",
            "warmup": 30,
            "craftable": false
        },
        {
            "id": "mothinduction",
            "label": "陳舊遙遠的不快之事",
            "actionId": "mothinduction",
            "effects": {
                "prerestlessness": 1
            },
            "startdescription": "蛾在黑暗中尋見光，我亦如是。",
            "description": "一種似有似無的惆悵染上了我。",
            "warmup": 30,
            "craftable": false
        },
        {
            "id": "mothglimmeringinduction",
            "label": "黑暗與光",
            "actionId": "mothinduction",
            "effects": {
                "preglimmering": 1
            },
            "startdescription": "蛾在黑暗中尋見光，我亦如是。",
            "description": "若不為此，何去何從？",
            "warmup": 30,
            "craftable": false
        },
        {
            "id": "grailinduction",
            "label": "欲望的背後",
            "actionId": "grailinduction",
            "effects": {
                "preglimmering": 1
            },
            "startdescription": "從滿足欲望的過程中能學到什麼嗎？",
            "description": "有種啟明般的感覺。",
            "warmup": 30,
            "craftable": false
        },
        {
            "id": "dreadinduction",
            "label": "暗夜驚魂",
            "actionId": "dreadinduction",
            "effects": {
                "predread": 1
            },
            "startdescription": "我在半夜驚醒。我的手掌，我的臉上都滲出汗珠。",
            "description": "慢慢地，我鬆開緊攥的拳頭。我又滑落回睡夢中。但某種東西留下了，好像房間角落的蛛網。",
            "warmup": 30,
            "craftable": false
        },
        {
            "id": "dreadinduction_ifdread",
            "label": "暗夜驚魂",
            "actionId": "dreadinduction",
            "requirements": {
                "dread": 1
            },
            "effects": {
                "predread": 1
            },
            "comments": "Only triggers if there's already Dread in whatever called this.",
            "startdescription": "我在半夜驚醒。我的手掌，我的臉上都滲出汗珠。",
            "description": "慢慢地，我鬆開緊攥的拳頭。我又滑落回睡夢中。但某種東西留下了，好像房間角落的蛛網。",
            "warmup": 30,
            "craftable": false
        },
        {
            "id": "fascinationinduction",
            "label": "新的色彩",
            "actionId": "fascinationinduction",
            "effects": {
                "prefascination": 1
            },
            "startdescription": "我開始留意世間那些我無法命名的色彩。",
            "description": "我正在看我不該看的東西。我知道這麼做的危險性，但要按捺住想看的念頭是很難的。",
            "warmup": 30,
            "craftable": false
        },
        {
            "id": "fascinationinduction_iffascination",
            "label": "新的色彩",
            "actionId": "fascinationinduction",
            "requirements": {
                "fascination": 1
            },
            "effects": {
                "prefascination": 1
            },
            "startdescription": "我開始留意世間那些我無法命名的色彩。",
            "description": "我正在看我不該看的東西。我知道這麼做的危險性，但要按捺住想看的念頭是很難的。",
            "warmup": 30,
            "craftable": false
        },
        {
            "id": "poison.notoriety.induction",
            "actionId": "poison.notoriety.induction",
            "label": "眾目睽睽",
            "startdescription": "我們派的追隨者有些過分出名了。防剿局也許會聽聞此事。",
            "effects": {
                "notoriety": 1
            },
            "warmup": 30
        },
        {
            "id": "poison.passion.dread.induction",
            "actionId": "poison.passion.dread.induction",
            "label": "滲人的顏色",
            "startdescription": "我的激情被毒侵入。每一陣精神上的劇痛都會喚起一陣兇猛的灰顏色。",
            "effects": {
                "dread": 1
            },
            "warmup": 30
        },
        {
            "id": "poison.reason.fascination.induction",
            "actionId": "poison.reason.fascination.induction",
            "label": "不息之光",
            "startdescription": "蠟燭，點火便會發光。我的思緒點燃時，會發生什麼？",
            "effects": {
                "fascination": 1
            },
            "warmup": 30
        },
        {
            "id": "poison.health.dread.induction",
            "actionId": "poison.health.dread.induction",
            "label": "款待痛苦",
            "startdescription": "我邀請一位老友在我的肌骨裡再居留一天。",
            "effects": {
                "dread": 1
            },
            "warmup": 30
        },
        {
            "id": "secret.induction",
            "actionId": "unsuspicion",
            "label": "隱私的好處",
            "startdescription": "我們已特意將總部設在某個冷僻無人的地方……",
            "description": "……也許能讓防剿局更難摸上門。要維持響亮的聲名可能也更難了。",
            "slots": [
                {
                    "id": "reputation",
                    "label": "聲名",
                    "required": {
                        "reputation": 1
                    },
                    "greedy": true
                }
            ],
            "warmup": 180,
            "effects": {
                "reputation": -1
            }
        }
    ]
}