{
	"recipes": [
		{
			"id": "studybenefactorwill",
			"label": "研究故人留下的文件",
			"startdescription": "當前的情況需要謹慎行事。在社會輿論中我們的關係並不正當。",
			"description": "我們兩人的關係從未公開。沒人會認為我能繼承一大筆遺產。然而，我仍分得了不少。"
		},
		{
			"id": "studybenefactorwill_suspicion",
			"label": ".",
			"description": "事情出了差錯。熟人們見我走來，便過街而去。報紙在暗示另有隱情。律師拒絕接見我。我已不必指望遺產，或許還有更糟的事在等著我。"
		},
		{
			"id": "study.welland.defeated",
			"label": "伊蘇斯重演",
			"startdescription": "我有機會和我們的塑形者成為敵人，正如獅子匠與上校那樣。[這將會使你先前的角色永遠不能飛升，但會給你機會贏得一場常規的<b>鑄</b>之勝利。除此之外沒有其他影響。]",
			"description": "忠誠的鎖鏈已然粉碎。我的追隨者不會起任何懷疑。等到我們的塑形者從流放中歸來時，非我消逝，然已不朽。"
		},
		{
			"id": "study.tryphon.defeated",
			"label": "極致的饗宴",
			"startdescription": "若我吞食特里豐女士的殘餘，我將不會被吞噬。[這將會使你先前的角色永遠不能飛升，但會給你機會贏得一場常規的<b>杯</b>之勝利。除此之外沒有其他影響。]",
			"description": "我們的愉悅者將無緣謝肉祭。我的追隨者將為我的欲望服務。此刻，由我吞噬，非被吞噬。"
		},
		{
			"id": "study.diarist.defeated",
			"label": "一門既閉",
			"startdescription": "日記作者給了我方法，可將我們的沐光明者棄於漫宿。[這將會使你先前的角色永遠不能飛升，但會給你機會贏得一場常規的<b>燈</b>之勝利。除此之外沒有其他影響。]",
			"description": "我已關上眼中的門扉，用蠟將其封死。那隻眼已盲，但另一隻眼看見了新的地平線。我們的組織將效力於另一個目標。或許有一天，我會與我們的創教者平起平坐。"
		},
		{
			"id": "study.julian.defeated",
			"label": "孤寂如虛",
			"startdescription": "我僅僅是“漫宿牆上的一塊石頭”？還有其他可能嗎？[這將會使你先前的角色永遠不能飛升，同時在牌桌上增加“恐懼”。除此之外沒有其他影響。]",
			"description": "我將依自己的選擇度過此生。我之所是，正是我將所為，直至不復存在。"
		}
	]
}