{
	"elements": [
		{
			"id": "investigator1",
			"label": "韋克菲爾德督察",
			"description": "柴克瑞·韋克菲爾德：一名悒悒不樂卻又冷酷無情的督察警官。他近期被借調至防剿局。"
		},
		{
			"id": "investigator2",
			"label": "斯賓塞·霍布森",
			"description": "霍布森當過記者、私家偵探，以及短暫當過教士。現在他是防剿局的一名特工。"
		},
		{
			"id": "investigator3",
			"label": "康妮·李",
			"description": "名門千金、女權運動者兼冒險家。她最近將那份堂吉訶德式的熱忱與龐大的財富，投入防剿局的事業。"
		},
		{
			"id": "investigator4",
			"label": "娜塔莉亞·龍博士",
			"description": "她因研究多重歷史而遭到嘲笑，被排擠出學術界，這反而讓她更加堅定。如今她與防剿局合作。"
		},
		{
			"id": "defaulthunter",
			"label": "疲憊的警探",
			"description": "這位紳士只想獨自抽著菸斗、讀著《倫敦新聞畫報》，但——<i>顯然</i>總得有人像抓瘋狗一樣去逮那種召喚怪物的傢伙，而且<i>顯然</i>只有他有空。"
		},
		{
			"id": "investigator1prisoner",
			"label": "韋克菲爾德督察：俘獲！",
			"description": "柴克瑞·韋克菲爾德：一名悒悒不樂卻又冷酷無情的督察警官。務必要讓他死在牢中。"
		},
		{
			"id": "investigator2prisoner",
			"label": "斯賓塞·霍布森：俘獲！",
			"description": "霍布森當過記者、私家偵探，以及短暫當過教士。務必要讓他死在牢中。"
		},
		{
			"id": "investigator3prisoner",
			"label": "康妮·李：俘獲！",
			"description": "名門千金、女權運動者兼冒險家。務必要讓她死在牢中。"
		},
		{
			"id": "investigator4prisoner",
			"label": "娜塔莉亞·龍博士：俘獲！",
			"description": "她因研究多重歷史而遭到嘲笑，被排擠出學術界，這反而讓她更加堅定。務必要讓她死在牢中。"
		},
		{
			"id": "defaulthunterprisoner",
			"label": "疲憊的警探：俘獲！",
			"description": "這位紳士只想獨自抽著菸斗、讀著《倫敦新聞畫報》，可惜現在卻被關在一個破爛地洞裡。"
		}
	]
}